PyMPDATA_MPI/__init__.py
PyMPDATA_MPI/domain_decomposition.py
PyMPDATA_MPI/hdf_storage.py
PyMPDATA_MPI/mpi_periodic.py
PyMPDATA_MPI/mpi_polar.py
PyMPDATA_MPI/utils.py
PyMPDATA_MPI/impl/__init__.py
PyMPDATA_MPI/impl/boundary_condition_commons.py
PyMPDATA_MPI/impl/mpi_boundary_condition.py
pympdata_mpi-1.6.3.dist-info/METADATA
pympdata_mpi-1.6.3.dist-info/WHEEL
pympdata_mpi-1.6.3.dist-info/top_level.txt
pympdata_mpi-1.6.3.dist-info/RECORD
