Metadata-Version: 2.4
Name: pympdata-mpi
Version: 1.6.3
Summary: PyMPDATA + numba-mpi coupler sandbox
License: GPL-3.0
Keywords: MPI,MPDATA,Numba,PyMPDATA
Classifier: Intended Audience :: Science/Research
Classifier: License :: OSI Approved :: GNU General Public License v3 (GPLv3)
Classifier: Operating System :: OS Independent
Classifier: Programming Language :: Python :: 3
Classifier: Topic :: Scientific/Engineering
Classifier: Topic :: Scientific/Engineering :: Atmospheric Science
Classifier: Topic :: Scientific/Engineering :: Mathematics
Classifier: Topic :: Scientific/Engineering :: Physics
Requires-Python: >=3.10
Requires-Dist: numba<0.57.0
Requires-Dist: numpy<1.25.0
Requires-Dist: numba_mpi>=0.30
Requires-Dist: PyMPDATA
Requires-Dist: mpi4py==4.0.3
Requires-Dist: h5py
Provides-Extra: tests
Requires-Dist: pytest; extra == "tests"
Requires-Dist: pytest-mpi; extra == "tests"
Requires-Dist: pytest-timeout; extra == "tests"
Requires-Dist: matplotlib; extra == "tests"
